topsis.py
topsis_sayyam_102303147-0.1.0.dist-info/licenses/LICENSE
topsis_sayyam_102303147-0.1.0.dist-info/METADATA
topsis_sayyam_102303147-0.1.0.dist-info/WHEEL
topsis_sayyam_102303147-0.1.0.dist-info/top_level.txt
topsis_sayyam_102303147-0.1.0.dist-info/RECORD
