Metadata-Version: 2.4
Name: topsis-sayyam-102303147
Version: 0.1.0
Summary: A command-line Python package implementing the TOPSIS method for multi-criteria decision making.
Home-page: https://github.com/Sayyam-wad/topsis-sayyam-102303147
Author: Sayyam Wadhwa
Author-email: sayyam.wad@gmail.com
License: MIT
Classifier: Development Status :: 5 - Production/Stable
Classifier: Intended Audience :: Education
Classifier: Topic :: Scientific/Engineering
Classifier: License :: OSI Approved :: MIT License
Classifier: Programming Language :: Python :: 3
Classifier: Operating System :: OS Independent
Requires-Python: >=3.8
License-File: LICENSE
Requires-Dist: numpy
Requires-Dist: pandas
Dynamic: author
Dynamic: author-email
Dynamic: classifier
Dynamic: description
Dynamic: description-content-type
Dynamic: home-page
Dynamic: license
Dynamic: license-file
Dynamic: requires-dist
Dynamic: requires-python
Dynamic: summary
